{"data-structure_sparse_array.md":"d9275643","go_enum.md":"547e3608","java_feign-global-config.md":"57aa9fc3","go_index.md":"b54651f7","data-structure_index.md":"e2532828","java_@springbootapplication.md":"9d5dee7c","go_common-library.md":"3ece7d71","index.md":"80fbb846","mq_kafka-install.md":"466c3517","mysql_index-lose-efficacy.md":"26dbb23a","mysql_index.md":"d6c0b22e","sundry_nginx-permission-denied.md":"aa708861","mq_index.md":"9d270ed8","sundry_docker-command.md":"50c15dc9","mysql_mysql-transaction.md":"c9991beb","data-structure_queue.md":"1ad1041d","sundry_centos-install-nginx.md":"6634457a","sundry_centos-yum.md":"fad32b0d","redis_index.md":"bfc3fcb3","java_index.md":"80fcdb1d","redis_cache.md":"9ce52534","java_thin-jar.md":"6a3e4c73","java_springboot-package.md":"4b29e9a3","sundry_git-command.md":"6a98797e","sundry_index.md":"95c1880b","sundry_install-zsh.md":"c6ec06b9","sundry_docker-install-redis.md":"2b7f4bde","sundry_linux-command.md":"1ddf1c3b"}
